birthdayculator/age_calculation.py
birthdayculator/delta_calculation.py
birthdayculator/input_conversion.py
birthdayculator/next_birthday_calculation.py
birthdayculator/stubs/assertpy/__init__.pyi
birthdayculator/stubs/assertpy/base.pyi
birthdayculator/stubs/assertpy/collection.pyi
birthdayculator/stubs/assertpy/contains.pyi
birthdayculator/stubs/assertpy/date.pyi
birthdayculator/stubs/assertpy/dict.pyi
birthdayculator/stubs/assertpy/dynamic.pyi
birthdayculator/stubs/assertpy/exception.pyi
birthdayculator/stubs/assertpy/extracting.pyi
birthdayculator/stubs/assertpy/file.pyi
birthdayculator/stubs/assertpy/helpers.pyi
birthdayculator/stubs/assertpy/numeric.pyi
birthdayculator/stubs/assertpy/snapshot.pyi
birthdayculator/stubs/assertpy/string.pyi
birthdayculator/stubs/dateutil/relativedelta.pyi
birthdayculator-0.5.0.dist-info/WHEEL
birthdayculator-0.5.0.dist-info/METADATA
birthdayculator-0.5.0.dist-info/RECORD
