Metadata-Version: 2.1
Name: birthdayculator
Version: 0.5.0
Summary: A thin and extremely specialised wrapper around luxon for calculating birthday info from a birth date. Ported from npm library
License: MIT
Author: Rick Cooper
Author-email: rcoops84@hotmail.com
Requires-Python: >=3.9,<4.0
Classifier: License :: OSI Approved :: MIT License
Classifier: Programming Language :: Python :: 3
Classifier: Programming Language :: Python :: 3.9
Classifier: Programming Language :: Python :: 3.10
Classifier: Programming Language :: Python :: 3.11
Requires-Dist: arrow (>=1.2.3,<2.0.0)
Requires-Dist: python-dateutil (>=2.8.2,<3.0.0)
